PyVarTools/__init__.py
PyVarTools/format_tools.py
PyVarTools/python_instances_tools.py
PyVarTools/var_utilities.py
PyVarTools/math/__init__.py
PyVarTools/math/basic_vars.py
PyVarTools/math/graph_2D.py
PyVarTools/math/vars.py
PyVarTools-1.4.1.dist-info/METADATA
PyVarTools-1.4.1.dist-info/WHEEL
PyVarTools-1.4.1.dist-info/top_level.txt
PyVarTools-1.4.1.dist-info/RECORD
